MAVProxy/__init__.py
MAVProxy/mavproxy.py
MAVProxy/modules/__init__.py
MAVProxy/modules/mavproxy_DGPS.py
MAVProxy/modules/mavproxy_GPSInject.py
MAVProxy/modules/mavproxy_GPSInput.py
MAVProxy/modules/mavproxy_HIL.py
MAVProxy/modules/mavproxy_OpenDroneID.py
MAVProxy/modules/mavproxy_SecureCommand.py
MAVProxy/modules/mavproxy_adsb.py
MAVProxy/modules/mavproxy_ais.py
MAVProxy/modules/mavproxy_antenna.py
MAVProxy/modules/mavproxy_arm.py
MAVProxy/modules/mavproxy_asterix.py
MAVProxy/modules/mavproxy_auxopt.py
MAVProxy/modules/mavproxy_battery.py
MAVProxy/modules/mavproxy_calibration.py
MAVProxy/modules/mavproxy_cameraview.py
MAVProxy/modules/mavproxy_checklist.py
MAVProxy/modules/mavproxy_cmdlong.py
MAVProxy/modules/mavproxy_console.py
MAVProxy/modules/mavproxy_dataflash_logger.py
MAVProxy/modules/mavproxy_devop.py
MAVProxy/modules/mavproxy_emuecu.py
MAVProxy/modules/mavproxy_example.py
MAVProxy/modules/mavproxy_fakegps.py
MAVProxy/modules/mavproxy_fence.py
MAVProxy/modules/mavproxy_fenceitem_protocol.py
MAVProxy/modules/mavproxy_firmware.py
MAVProxy/modules/mavproxy_followtest.py
MAVProxy/modules/mavproxy_ftp.py
MAVProxy/modules/mavproxy_gasheli.py
MAVProxy/modules/mavproxy_generator.py
MAVProxy/modules/mavproxy_genobstacles.py
MAVProxy/modules/mavproxy_gimbal.py
MAVProxy/modules/mavproxy_gopro.py
MAVProxy/modules/mavproxy_graph.py
MAVProxy/modules/mavproxy_heliplane.py
MAVProxy/modules/mavproxy_help.py
MAVProxy/modules/mavproxy_horizon.py
MAVProxy/modules/mavproxy_instructor.py
MAVProxy/modules/mavproxy_kmlread.py
MAVProxy/modules/mavproxy_layout.py
MAVProxy/modules/mavproxy_link.py
MAVProxy/modules/mavproxy_log.py
MAVProxy/modules/mavproxy_message.py
MAVProxy/modules/mavproxy_messagerate.py
MAVProxy/modules/mavproxy_misc.py
MAVProxy/modules/mavproxy_mode.py
MAVProxy/modules/mavproxy_movinghome.py
MAVProxy/modules/mavproxy_mqtt.py
MAVProxy/modules/mavproxy_msg.py
MAVProxy/modules/mavproxy_nmeagps.py
MAVProxy/modules/mavproxy_nmeaout.py
MAVProxy/modules/mavproxy_nsh.py
MAVProxy-1.8.71.dist-info/COPYING.txt
MAVProxy-1.8.71.dist-info/METADATA
MAVProxy-1.8.71.dist-info/WHEEL
MAVProxy-1.8.71.dist-info/top_level.txt
MAVProxy-1.8.71.dist-info/zip-safe
MAVProxy-1.8.71.dist-info/RECORD
