Metadata-Version: 2.1
Name: MAVProxy
Version: 1.8.71
Summary: MAVProxy MAVLink ground station
Home-page: https://github.com/ArduPilot/MAVProxy
Author: Andrew Tridgell
Author-email: andrew@tridgell.net
License: GPLv3
Classifier: Development Status :: 5 - Production/Stable
Classifier: Environment :: Console
Classifier: Intended Audience :: Science/Research
Classifier: License :: OSI Approved :: GNU General Public License v3 (GPLv3)
Classifier: Operating System :: OS Independent
Classifier: Programming Language :: Python
Classifier: Topic :: Scientific/Engineering
License-File: COPYING.txt
Requires-Dist: pymavlink>=2.4.14
Requires-Dist: pyserial>=3.0
Requires-Dist: numpy
Requires-Dist: pynmeagps
Provides-Extra: server
Requires-Dist: flask; extra == "server"
Provides-Extra: recommended
Requires-Dist: flask; extra == "recommended"
Requires-Dist: PyYAML; extra == "recommended"
Requires-Dist: lxml; extra == "recommended"
Requires-Dist: wxpython; extra == "recommended"
Requires-Dist: pymonocypher; extra == "recommended"
Requires-Dist: openai; extra == "recommended"
Requires-Dist: paho-mqtt; extra == "recommended"
Requires-Dist: piexif; extra == "recommended"
Requires-Dist: pynmea2; extra == "recommended"
Requires-Dist: Pygame; extra == "recommended"
Requires-Dist: Pillow; extra == "recommended"
